{"updated":"2026-07-14T17:57:40.322064+00:00","tickers":{"BB":{"price":11.055,"change1d":3.22,"atr_pct":9.27,"adr_pct":7.98,"ema21d":4.68,"sma50d":25.51,"sma200d":110.27,"rel_vol":0.48},"CHRW":{"price":198.91,"change1d":1.23,"atr_pct":2.52,"adr_pct":2.84,"ema21d":5.32,"sma50d":10.18,"sma200d":18.91,"rel_vol":0.63},"GRND":{"price":15.63,"change1d":-0.13,"atr_pct":5.21,"adr_pct":4.89,"ema21d":6.64,"sma50d":15.66,"sma200d":20.4,"rel_vol":0.17},"META":{"price":661.47,"change1d":0.72,"atr_pct":4.18,"adr_pct":3.52,"ema21d":8.7,"sma50d":10.09,"sma200d":3.24,"rel_vol":0.37},"TLN":{"price":396.635,"change1d":0.07,"atr_pct":4.83,"adr_pct":4.84,"ema21d":2.89,"sma50d":4.77,"sma200d":6.9,"rel_vol":0.39},"AAPL":{"price":315.14,"change1d":-0.68,"atr_pct":2.85,"adr_pct":2.65,"ema21d":3.56,"sma50d":5.2,"sma200d":15.55,"rel_vol":0.28}}}